casdbops/__init__.py
casdbops/cassandra_crud.py
tests/__init__.py
tests/integration/__init__.py
tests/integration/test_int.py
tests/unit/__init__.py
tests/unit/test_unit.py
casdbops-0.0.4.dist-info/METADATA
casdbops-0.0.4.dist-info/WHEEL
casdbops-0.0.4.dist-info/top_level.txt
casdbops-0.0.4.dist-info/RECORD
