Metadata-Version: 2.1
Name: casdbops
Version: 0.0.4
Summary: A python package for connecting with database.
Home-page: https://github.com/pranav-c01/cassandraconnectorpkg
Author: pranav-c01
Author-email: pranavc430@gmail.com
License: MIT
Project-URL: Bug Tracker, https://github.com/pranav-c01/cassandraconnectorpkg/issues
Classifier: Programming Language :: Python :: 3.8
Classifier: Programming Language :: Python :: 3.9
Classifier: Operating System :: OS Independent
Requires-Python: >=3.8
Requires-Dist: astrapy ==0.7.7
Requires-Dist: pandas
Requires-Dist: numpy
Requires-Dist: ensure
Requires-Dist: pytest ==7.1.3
Provides-Extra: testing
Requires-Dist: pytest >=7.1.3 ; extra == 'testing'
Requires-Dist: tox >=3.25.1 ; extra == 'testing'
Requires-Dist: flake8 >=5.0.4 ; extra == 'testing'
Requires-Dist: black >=22.8.0 ; extra == 'testing'
